monite/__init__.py
monite/access_tokens/__init__.py
monite/access_tokens/client.py
monite/access_tokens/raw_client.py
monite/accounting/__init__.py
monite/accounting/client.py
monite/accounting/connections/__init__.py
monite/accounting/connections/client.py
monite/accounting/connections/raw_client.py
monite/accounting/ledger_accounts/__init__.py
monite/accounting/ledger_accounts/client.py
monite/accounting/ledger_accounts/raw_client.py
monite/accounting/payables/__init__.py
monite/accounting/payables/client.py
monite/accounting/payables/raw_client.py
monite/accounting/raw_client.py
monite/accounting/receivables/__init__.py
monite/accounting/receivables/client.py
monite/accounting/receivables/raw_client.py
monite/accounting/synced_records/__init__.py
monite/accounting/synced_records/client.py
monite/accounting/synced_records/raw_client.py
monite/accounting/tax_rates/__init__.py
monite/accounting/tax_rates/client.py
monite/accounting/tax_rates/raw_client.py
monite/analytics/__init__.py
monite/analytics/client.py
monite/analytics/raw_client.py
monite/analytics/types/__init__.py
monite/analytics/types/get_analytics_receivables_request_status.py
monite/analytics/types/get_analytics_receivables_request_status_in_item.py
monite/approval_policies/__init__.py
monite/approval_policies/client.py
monite/approval_policies/processes/__init__.py
monite/approval_policies/processes/client.py
monite/approval_policies/processes/raw_client.py
monite/approval_policies/raw_client.py
monite/approval_policies/types/__init__.py
monite/approval_policies/types/approval_policies_get_request_status.py
monite/approval_policies/types/approval_policies_get_request_status_in_item.py
monite/approval_policies/types/approval_policy_create_script_item.py
monite/approval_policies/types/approval_policy_create_trigger.py
monite/approval_policies/types/approval_policy_update_script_item.py
monite/approval_policies/types/approval_policy_update_trigger.py
monite/approval_requests/__init__.py
monite-0.5.4.dist-info/LICENSE
monite-0.5.4.dist-info/METADATA
monite-0.5.4.dist-info/WHEEL
monite-0.5.4.dist-info/RECORD
